noaawc/__init__.py
noaawc/animate.py
noaawc/main.py
noaawc/plot.py
noaawc/video.py
tests/__init__.py
noaawc-0.2.1.dist-info/LICENSE
noaawc-0.2.1.dist-info/METADATA
noaawc-0.2.1.dist-info/WHEEL
noaawc-0.2.1.dist-info/top_level.txt
noaawc-0.2.1.dist-info/RECORD
