Metadata-Version: 2.1
Name: noaawc
Version: 0.2.1
Summary: Library for plotting dataset from noaa site in basemap
Home-page: https://github.com/reinanbr/noaawc
Author: Reinan Br
Author-email: slimchatuba@gmail.com
License: GPLv3
Keywords: climate weather noaa plots
License-File: LICENSE
Requires-Dist: pygrib
Requires-Dist: kitano
Requires-Dist: numpy
Requires-Dist: noawclg
Requires-Dist: matplotlib
Requires-Dist: pandas
Requires-Dist: animateplot
Requires-Dist: psutil
Requires-Dist: imageio
Requires-Dist: basemap
